pman/__init__.py
pman/__main__.py
pman/_build.py
pman/_core.py
pman/_utils.py
pman/build_apps.py
pman/cli.py
pman/config.py
pman/creationutils.py
pman/exceptions.py
pman/native2bam.py
pman/setuptools.py
pman/shim.py
pman/version.py
pman/plugins/__init__.py
pman/plugins/blend2bam.py
pman/plugins/common.py
pman/plugins/copyfile.py
pman/plugins/native2bam.py
pman/templates/main.py
pman/templates/pyproject.toml
pman/templates/test_imports.py
panda3d_pman-0.16.0.dist-info/LICENSE.txt
panda3d_pman-0.16.0.dist-info/METADATA
panda3d_pman-0.16.0.dist-info/WHEEL
panda3d_pman-0.16.0.dist-info/entry_points.txt
panda3d_pman-0.16.0.dist-info/top_level.txt
panda3d_pman-0.16.0.dist-info/RECORD
