Metadata-Version: 2.1
Name: panda3d-pman
Version: 0.16.0
Summary: A Python package to help bootstrap and manage Panda3D applications
Author: Mitchell Stokes
License: MIT
Project-URL: homepage, https://github.com/Moguri/pman
Keywords: panda3d,gamedev
Classifier: Development Status :: 4 - Beta
Classifier: License :: OSI Approved :: MIT License
Classifier: Programming Language :: Python :: 3
Requires-Python: >=3.8
License-File: LICENSE.txt
Requires-Dist: panda3d-blend2bam >=0.22.0
Requires-Dist: tomli >=2.0.1
Requires-Dist: rich ~=13.5.0
Requires-Dist: setuptools ; python_version >= "3.12"
Provides-Extra: test
Requires-Dist: panda3d ; extra == 'test'
Requires-Dist: pytest ; extra == 'test'
Requires-Dist: pylint ~=2.17.0 ; extra == 'test'
Requires-Dist: pytest-pylint ; extra == 'test'
